{
  "scenario_name": "multi_merge_rain_107",
  "description": "Multiple vehicles merging in rain with varied speeds",
  "weather": "mid_rain",
  "ego_vehicle_model": "vehicle.citroen.c3",
  "ego_spawn": {
    "criteria": {
      "lane_type": "Driving",
      "road_context": "highway",
      "speed_limit": {"min": 85, "max": 110},
      "is_intersection": false
    }
  },
  "ego_start_speed": 19,
  "actors": [
    {
      "id": "early_merger",
      "type": "vehicle",
      "model": "vehicle.toyota.prius",
      "spawn": {
        "criteria": {
          "lane_type": "Driving",
          "road_context": "highway",
          "distance_to_ego": {"min": 100, "max": 120},
          "relative_position": "ahead",
          "road_relationship": "same_road",
          "lane_relationship": "adjacent_lane"
        }
      },
      "color": "50,200,50"
    },
    {
      "id": "late_merger",
      "type": "vehicle",
      "model": "vehicle.jeep.wrangler_rubicon",
      "spawn": {
        "criteria": {
          "lane_type": "Driving",
          "road_context": "highway",
          "distance_to_ego": {"min": 65, "max": 80},
          "relative_position": "ahead",
          "road_relationship": "same_road",
          "lane_relationship": "adjacent_lane"
        }
      },
      "color": "200,150,0"
    },
    {
      "id": "aggressive_merger",
      "type": "vehicle",
      "model": "vehicle.seat.leon",
      "spawn": {
        "criteria": {
          "lane_type": "Driving",
          "road_context": "highway",
          "distance_to_ego": {"min": 40, "max": 50},
          "relative_position": "behind",
          "road_relationship": "same_road",
          "lane_relationship": "adjacent_lane"
        }
      },
      "color": "255,100,100"
    }
  ],
  "actions": [
    {
      "actor_id": "early_merger",
      "action_type": "lane_change",
      "trigger_type": "time",
      "trigger_value": 2.0,
      "target_lane": -1,
      "dynamics_dimension": "distance",
      "dynamics_shape": "cubic",
      "dynamics_value": 70.0
    },
    {
      "actor_id": "late_merger",
      "action_type": "speed",
      "trigger_type": "time",
      "trigger_value": 1.5,
      "speed_value": 17.0,
      "dynamics_dimension": "time",
      "dynamics_shape": "linear",
      "dynamics_value": 3.0
    },
    {
      "actor_id": "aggressive_merger",
      "action_type": "speed",
      "trigger_type": "time",
      "trigger_value": 0.5,
      "speed_value": 24.0,
      "dynamics_dimension": "time",
      "dynamics_shape": "cubic",
      "dynamics_value": 2.5
    },
    {
      "actor_id": "late_merger",
      "action_type": "lane_change",
      "trigger_type": "after_previous",
      "target_lane": -1,
      "dynamics_dimension": "time",
      "dynamics_shape": "sinusoidal",
      "dynamics_value": 4.5
    },
    {
      "actor_id": "aggressive_merger",
      "action_type": "lane_change",
      "trigger_type": "distance_to_ego",
      "trigger_value": 20.0,
      "trigger_comparison": "<",
      "target_lane": -1,
      "dynamics_dimension": "time",
      "dynamics_shape": "cubic",
      "dynamics_value": 2.0
    },
    {
      "actor_id": "early_merger",
      "action_type": "brake",
      "trigger_type": "distance_to_ego",
      "trigger_value": 30.0,
      "trigger_comparison": "<",
      "brake_force": 0.5
    }
  ],
  "success_distance": 170,
  "timeout": 95,
  "collision_allowed": false
}