{
  "scenario_name": "rain_following_wet_22",
  "description": "Vehicle following in wet roads after rain",
  "weather": "wet",
  "ego_vehicle_model": "vehicle.audi.a2",
  "ego_spawn": {
    "criteria": {
      "lane_type": "Driving",
      "lane_id": {
        "min": 1,
        "max": 10
      },
      "is_intersection": false
    }
  },
  "ego_start_speed": 2,
  "actors": [
    {
      "id": "lead_vehicle",
      "type": "vehicle",
      "model": "vehicle.bh.crossbike",
      "spawn": {
        "criteria": {
          "lane_type": "Driving",
          "road_relationship": "same_road",
          "lane_relationship": "same_lane",
          "distance_to_ego": {
            "min": 40,
            "max": 55
          },
          "relative_position": "ahead"
        }
      }
    }
  ],
  "actions": [
    {
      "actor_id": "lead_vehicle",
      "action_type": "speed",
      "trigger_type": "distance_to_ego",
      "trigger_value": 40,
      "trigger_comparison": "<",
      "speed_value": 10.2,
      "dynamics_dimension": "time",
      "dynamics_value": 3.0
    },
    {
      "actor_id": "lead_vehicle",
      "action_type": "speed",
      "trigger_type": "after_previous",
      "speed_value": 6.8,
      "dynamics_dimension": "time",
      "dynamics_value": 4.0
    }
  ],
  "success_distance": 89,
  "timeout": 110,
  "collision_allowed": false
}