{
  "scenario_name": "delivery_truck_stopped_19",
  "description": "Delivery truck stopped in lane",
  "weather": "hard_rain",
  "ego_vehicle_model": "vehicle.audi.a2",
  "ego_spawn": {
    "criteria": {
      "lane_type": "Driving",
      "lane_id": {
        "min": 1,
        "max": 10
      },
      "is_intersection": false
    }
  },
  "ego_start_speed": 0,
  "actors": [
    {
      "id": "obstacle",
      "type": "vehicle",
      "model": "vehicle.mercedes.sprinter",
      "spawn": {
        "criteria": {
          "lane_type": "Driving",
          "distance_to_ego": {
            "min": 57,
            "max": 67
          },
          "relative_position": "ahead"
        }
      }
    }
  ],
  "actions": [],
  "success_distance": 111,
  "timeout": 65,
  "collision_allowed": false
}